greyhorse_sqla/__init__.py
greyhorse_sqla/config.py
greyhorse_sqla/contexts.py
greyhorse_sqla/controllers.py
greyhorse_sqla/engine_async.py
greyhorse_sqla/engine_sync.py
greyhorse_sqla/factory.py
greyhorse_sqla/py.typed
greyhorse_sqla/query.py
greyhorse_sqla/repositories.py
greyhorse_sqla/repository_async.py
greyhorse_sqla/repository_sync.py
greyhorse_sqla/services.py
greyhorse_sqla/translations.toml
greyhorse_sqla/migration/__init__.py
greyhorse_sqla/migration/cmd.py
greyhorse_sqla/migration/operator.py
greyhorse_sqla/migration/service.py
greyhorse_sqla/migration/utils.py
greyhorse_sqla/migration/visitor.py
greyhorse_sqla-0.4.26.dist-info/METADATA
greyhorse_sqla-0.4.26.dist-info/WHEEL
greyhorse_sqla-0.4.26.dist-info/entry_points.txt
greyhorse_sqla-0.4.26.dist-info/RECORD
